tool_search/__init__.py
tool_search/cache.py
tool_search/connection.py
tool_search/demo.py
tool_search/errors.py
tool_search/examples_loader.py
tool_search/indexer.py
tool_search/py.typed
tool_search/searcher.py
tool_search/server.py
tool_search/auth/__init__.py
tool_search/auth/http_client.py
tool_search/auth/keyring_provider.py
tool_search/config/upstream_servers.json
tool_search/examples/.gitkeep
tool_search/examples/linear.yaml
tool_search/scripts/discover_keyring.py
tool_search-0.1.2.dist-info/METADATA
tool_search-0.1.2.dist-info/WHEEL
tool_search-0.1.2.dist-info/entry_points.txt
tool_search-0.1.2.dist-info/licenses/LICENSE
tool_search-0.1.2.dist-info/RECORD
