Metadata-Version: 2.4
Name: tool-search
Version: 0.1.2
Summary: MCP server for semantic tool discovery and invocation across multiple MCP servers
Project-URL: Homepage, https://github.com/alexandme/droid-advanced-tools
Project-URL: Repository, https://github.com/alexandme/droid-advanced-tools
Project-URL: Issues, https://github.com/alexandme/droid-advanced-tools/issues
Author: Sasha Alyushin
License-Expression: MIT
License-File: LICENSE
Keywords: anthropic,claude,embeddings,mcp,semantic-search,tool-search
Classifier: Development Status :: 4 - Beta
Classifier: Intended Audience :: Developers
Classifier: License :: OSI Approved :: MIT License
Classifier: Programming Language :: Python :: 3
Classifier: Programming Language :: Python :: 3.12
Classifier: Programming Language :: Python :: 3.13
Classifier: Topic :: Software Development :: Libraries :: Python Modules
Classifier: Typing :: Typed
Requires-Python: >=3.12
Requires-Dist: httpx>=0.27.0
Requires-Dist: jsonschema>=4.20.0
Requires-Dist: keyring>=24.0.0
Requires-Dist: mcp>=1.0.0
Requires-Dist: numpy>=1.24.0
Requires-Dist: pyyaml>=6.0.0
Requires-Dist: sentence-transformers>=2.2.0
